datavalid/__init__.py
datavalid/__main__.py
datavalid/checkers.py
datavalid/column_schema.py
datavalid/condition.py
datavalid/config.py
datavalid/date.py
datavalid/exceptions.py
datavalid/field_checkers.py
datavalid/file.py
datavalid/filter.py
datavalid/group_by.py
datavalid/schema.py
datavalid/spinner.py
datavalid/task.py
datavalid/test_checkers.py
datavalid/test_column_schema.py
datavalid/test_condition.py
datavalid/test_config.py
datavalid/test_date.py
datavalid/test_field_checkers.py
datavalid/test_file.py
datavalid/test_filter.py
datavalid/test_group_by.py
datavalid/test_schema.py
datavalid/test_task.py
datavalid/testing.py
datavalid/utils.py
datavalid-0.3.6.dist-info/LICENSE
datavalid-0.3.6.dist-info/METADATA
datavalid-0.3.6.dist-info/WHEEL
datavalid-0.3.6.dist-info/top_level.txt
datavalid-0.3.6.dist-info/RECORD
