Metadata-Version: 2.1
Name: datavalid
Version: 0.3.6
Summary: Data validation library
Home-page: https://github.com/pckhoi/datavalid
Author: Khoi Pham
Author-email: pckhoi@gmail.com
License: UNKNOWN
Project-URL: Bug Tracker, https://github.com/pckhoi/datavalid/issues
Platform: UNKNOWN
Classifier: Programming Language :: Python :: 3
Classifier: License :: OSI Approved :: MIT License
Classifier: Operating System :: OS Independent
Requires-Python: >=3.8
License-File: LICENSE
Requires-Dist: numpy (>=1.18)
Requires-Dist: pandas (>=1.2)
Requires-Dist: pyyaml (>=5.4.1)
Requires-Dist: termcolor (>=1.1.0)
